pyjason/__init__.py
pyjason/shop.py
pyjason/test.py
pyjason-0.4.dist-info/METADATA
pyjason-0.4.dist-info/RECORD
pyjason-0.4.dist-info/WHEEL
pyjason-0.4.dist-info/top_level.txt
