Metadata-Version: 2.1
Name: pyjason
Version: 0.4
Summary: pyjason is a hello world practise from pyjason
Home-page: http://github.com/liveget/pyjason
Author: PyJason
Author-email: liveget.com@gmail.com
License: MIT
Platform: UNKNOWN
